cpskin/__init__.py
cpskin/theme/__init__.py
cpskin/theme/configure.zcml
cpskin/theme/interfaces.py
cpskin/theme/profiles.zcml
cpskin/theme/setuphandlers.py
cpskin/theme/testing.py
cpskin/theme/testing.zcml
cpskin/theme/upgradehandlers.py
cpskin/theme/browser/__init__.py
cpskin/theme/browser/configure.zcml
cpskin/theme/browser/diazo.py
cpskin/theme/profiles/default/browserlayer.xml
cpskin/theme/profiles/default/cpskin.theme-default.txt
cpskin/theme/profiles/default/cssregistry.xml
cpskin/theme/profiles/default/import_steps.xml
cpskin/theme/profiles/default/lessregistry.xml
cpskin/theme/profiles/default/metadata.xml
cpskin/theme/profiles/default/registry.xml
cpskin/theme/profiles/testing/metadata.xml
cpskin/theme/profiles/uninstall/browserlayer.xml
cpskin/theme/profiles/uninstall/cpskin.theme-uninstall.txt
cpskin/theme/profiles/uninstall/cssregistry.xml
cpskin/theme/profiles/uninstall/import_steps.xml
cpskin/theme/profiles/uninstall/lessregistry.xml
cpskin/theme/static/manifest.cfg
cpskin/theme/static/preview.png
cpskin/theme/static/rules.xml
cpskin/theme/static/css/citizen.css
cpskin/theme/static/css/fontello.css
cpskin/theme/static/css/mobile.css
cpskin/theme/static/css/mobilelarge.css
cpskin/theme/static/css/mobilemedium.css
cpskin/theme/static/css/print.css
cpskin/theme/static/css/styles.css
cpskin/theme/static/font/fontello.eot
cpskin/theme/static/font/fontello.svg
cpskin/theme/static/font/fontello.ttf
cpskin/theme/static/font/fontello.woff
cpskin/theme/static/font/fontello.woff2
cpskin/theme/static/images/bookmark.png
cpskin/theme/static/images/camera.png
cpskin/theme/static/images/horloge.png
cpskin/theme/static/images/media-bg.gif
cpskin/theme/static/images/searchbt.png
cpskin/theme/static/images/site-de.jpg
cpskin/theme/static/images/site-en.jpg
cpskin/theme/static/images/site-nl.jpg
cpskin/theme/static/less/contact.less
cpskin/theme/static/less/mobile.less
cpskin/theme/static/less/mobilelarge.less
cpskin.theme-0.6.54.dist-info/DESCRIPTION.rst
cpskin.theme-0.6.54.dist-info/METADATA
cpskin.theme-0.6.54.dist-info/RECORD
cpskin.theme-0.6.54.dist-info/WHEEL
cpskin.theme-0.6.54.dist-info/metadata.json
cpskin.theme-0.6.54.dist-info/top_level.txt
