Metadata-Version: 2.0
Name: cpskin.theme
Version: 0.6.54
Summary: Theme package for cpskin
Home-page: https://github.com/imio/
Author: IMIO
Author-email: support@imio.be
License: gpl
Platform: UNKNOWN
Classifier: Environment :: Web Environment
Classifier: Programming Language :: Python
Classifier: Programming Language :: Python :: 2.7
Classifier: Framework :: Plone
Classifier: Framework :: Plone :: 4.2
Classifier: Framework :: Plone :: 4.3
Provides-Extra: test
Requires-Dist: setuptools
Requires-Dist: Plone
Requires-Dist: plone.api
Requires-Dist: plone.app.theming
Requires-Dist: diazotheme.frameworks
Requires-Dist: collective.lesscss
Requires-Dist: cpskin.core
Requires-Dist: cpskin.locales
Requires-Dist: z3c.jbot
Requires-Dist: collective.themefragments
Provides-Extra: test
Requires-Dist: plone.app.testing; extra == 'test'
Requires-Dist: unittest2; extra == 'test'
